fastapi_sa/__init__.py
fastapi_sa/database.py
fastapi_sa/exceptions.py
fastapi_sa/middleware.py
fastapi_sa-0.2.0.dist-info/LICENSE
fastapi_sa-0.2.0.dist-info/METADATA
fastapi_sa-0.2.0.dist-info/WHEEL
fastapi_sa-0.2.0.dist-info/RECORD
