Metadata-Version: 2.1
Name: fastapi-sa
Version: 0.2.0
Summary: fastapi-sa provides a simple integration between FastAPI and SQLAlchemy in your application
License: MIT
Author: huagang
Author-email: huagang517@126.com
Requires-Python: >=3.10,<4.0
Classifier: License :: OSI Approved :: MIT License
Classifier: Operating System :: OS Independent
Classifier: Programming Language :: Python :: 3
Classifier: Programming Language :: Python :: 3.10
Classifier: Programming Language :: Python :: 3.11
Classifier: Programming Language :: Python :: 3.12
Requires-Dist: sqlalchemy[asyncio] (>=2.0.23,<3.0.0)
